TEvarSim/TE_real.py
TEvarSim/TEpan.py
TEvarSim/__init__.py
TEvarSim/__main__.py
TEvarSim/build_pool.py
TEvarSim/compare_vcf.py
TEvarSim/reads.py
TEvarSim/simulate.py
TEvarSim/utils.py
tevarsim-1.0.2.dist-info/licenses/LICENSE
tevarsim-1.0.2.dist-info/METADATA
tevarsim-1.0.2.dist-info/WHEEL
tevarsim-1.0.2.dist-info/entry_points.txt
tevarsim-1.0.2.dist-info/top_level.txt
tevarsim-1.0.2.dist-info/RECORD
